ctodo.py
ctodo-1.0.2.dist-info/DESCRIPTION.rst
ctodo-1.0.2.dist-info/METADATA
ctodo-1.0.2.dist-info/RECORD
ctodo-1.0.2.dist-info/WHEEL
ctodo-1.0.2.dist-info/entry_points.txt
ctodo-1.0.2.dist-info/metadata.json
ctodo-1.0.2.dist-info/top_level.txt
