Metadata-Version: 2.0
Name: ctodo
Version: 1.0.2
Summary: A simple command line todo list
Home-page: https://gitlab.com/marcobius/console_todo
Author: Marcobius
Author-email: marcobius@gmail.com
License: MIT
Keywords: command line todo list
Platform: UNKNOWN
Classifier: Development Status :: 4 - Beta
Classifier: Intended Audience :: Developers
Classifier: Topic :: Utilities
Classifier: License :: OSI Approved :: MIT License
Classifier: Programming Language :: Python :: 2
Classifier: Programming Language :: Python :: 2.7
Classifier: Programming Language :: Python :: 3
Classifier: Programming Language :: Python :: 3.3
Classifier: Programming Language :: Python :: 3.4
Classifier: Programming Language :: Python :: 3.5
Requires-Dist: tinydb
